nepalilang/__init__.py
nepalilang/nepalilang.py
nepalilang-0.2.0.dist-info/LICENSE
nepalilang-0.2.0.dist-info/METADATA
nepalilang-0.2.0.dist-info/WHEEL
nepalilang-0.2.0.dist-info/top_level.txt
nepalilang-0.2.0.dist-info/RECORD
