Metadata-Version: 2.2
Name: nepalilang
Version: 0.2.0
Summary: A Nepali-language implementation
Home-page: https://github.com/Beasova-Corporation/Ilbpp.git
Author: Ujjwal Kumar Rajak
Author-email: ujjwalrajak2002@gmail.com
License: MIT
Classifier: Programming Language :: Python :: 3
Classifier: License :: OSI Approved :: MIT License
Classifier: Operating System :: OS Independent
Requires-Python: >=3.6
License-File: LICENSE
Dynamic: author
Dynamic: author-email
Dynamic: classifier
Dynamic: description
Dynamic: description-content-type
Dynamic: home-page
Dynamic: license
Dynamic: requires-python
Dynamic: summary
